mcp_obsidian/__init__.py
mcp_obsidian/obsidian.py
mcp_obsidian/server.py
mcp_obsidian/tools.py
mcp_obsidian-0.2.2.dist-info/METADATA
mcp_obsidian-0.2.2.dist-info/WHEEL
mcp_obsidian-0.2.2.dist-info/entry_points.txt
mcp_obsidian-0.2.2.dist-info/licenses/LICENSE
mcp_obsidian-0.2.2.dist-info/RECORD
